undetected_webdriver/browser.py
undetected_webdriver-1.2.dist-info/LICENSE
undetected_webdriver-1.2.dist-info/METADATA
undetected_webdriver-1.2.dist-info/WHEEL
undetected_webdriver-1.2.dist-info/top_level.txt
undetected_webdriver-1.2.dist-info/RECORD
