Metadata-Version: 2.1
Name: undetected_webdriver
Version: 1.2
Summary: An undetected version of better selenium.
Author-email: Izaan Noman <izaan.nyc@gmail.com>
Project-URL: Homepage, https://github.com/pypa/sampleproject
Project-URL: Bug Tracker, https://github.com/pypa/sampleproject/issues
Classifier: Programming Language :: Python :: 3
Classifier: License :: OSI Approved :: MIT License
Classifier: Operating System :: OS Independent
Requires-Python: >=3.7
License-File: LICENSE
Requires-Dist: undetected-chromedriver >=3.5.4
Requires-Dist: setuptools >=61.1.0
Requires-Dist: disutils
